MANIFEST.in
README.rst
setup.py
ahlev_django_auth_rename.egg-info/PKG-INFO
ahlev_django_auth_rename.egg-info/SOURCES.txt
ahlev_django_auth_rename.egg-info/dependency_links.txt
ahlev_django_auth_rename.egg-info/not-zip-safe
ahlev_django_auth_rename.egg-info/top_level.txt
auth_rename/__init__.py
auth_rename/admin.py
auth_rename/apps.py
auth_rename/models.py
auth_rename/tests.py
auth_rename/views.py